{
 "slug": "pohjantahti",
 "hintalaskuri_ilman_yhteystietoja": "osittain",
 "vakuutusehdot_saatavilla": "kylla",
 "omavastuu_selkeasti": "ei",
 "korvausprosessi_kuvattu": "osittain",
 "y_tunnus_esilla": "kylla",
 "y_tunnus": "0146905-4",
 "riippumaton_arvio": "ei",
 "asiakasarvio": {"arvosana": 8.1, "maara": null, "lahde": null},
 "puhelin_esilla": "kylla",
 "puhelin": "020 763 4010",
 "email_esilla": "osittain",
 "chat_mainittu": "ei",
 "aukioloajat_esilla": "kylla",
 "ukk_osio": "kylla",
 "mobiilisovellus": "osittain",
 "vakuutuslajit": ["koti","auto","matka","vene","hevonen","lemmiikki","henki","terveys","tapaturma","oikeusturva","metsä","asuntovaunut"],
 "ai_arviot": {"selkeys": 70, "hintojen_loydettavyys": 60, "sisallon_kattavuus": 65},
 "vahvuudet": ["Kaikki vakuutusehdot ja tuoteselosteet ladattavissa PDF-muodossa ilman kirjautumista","130 vuotta toimintaa, selkeä Y-tunnus ja yrityksen tiedot esillä","24/7 digitaalinen palvelu Oma Pohjantähti -portaalin kautta"],
 "kehityskohteet": ["Omavastuut eivät näy julkisilla sivuilla, vaan ainoastaan PDF-ehdoissa","Vahinkojen korvaamisen prosessia ei kuvattu selkeästi ilman kirjautumista","Hintoja saatavilla vain henkilötunnuksella ja postinumerolla, kotivakuutuksille ei hintalaskuria"],
 "yhteenveto": "Pohjantähti on 130 vuotta toiminut keskinäinen vakuutusyhtiö, joka tarjoaa laajasti henkilö- ja yritysasiakkaiden vakuutuksia. Verkkosivusto on selkeästi rakennettu kotimaisen vakuutuspalvelun ja neljän kanavan (puhelin, sähköposti, verkkopalvelu, henkilökohtainen neuvoja) kanssa, mutta tärkeät tiedot kuten omavastuut ja korvaamisprosessin yksityiskohdat on piilotettu PDF-asiakirjojen ja kirjautumisen taakse. Autovakuutuksen hintalaskuri toimii ilman yhteystietoja, mutta vaatii henkilötunnuksen.",
 "evidence": {
  "hintalaskuri_ilman_yhteystietoja": "Vaatii rekisteröintinumeron ja henkilötunnuksen, mutta ei nimeä, sähköpostia tai puhelinnumeroa",
  "omavastuu_selkeasti": "Listaus vakuutusehdot ja tuoteselosteet -sivulla ei näytä niiden sisältöä",
  "riippumaton_arvio": "8.1 Asiakkaiden arvio palvelustamme - ei mainintaa lähteestä kuten Trustpilot tai EPSI Rating"
 }
}